WeReadScan/WeRead.py
WeReadScan/__init__.py
WeReadScan/script/__init__.py
WeReadScan/script/os_util.py
WeReadScan/script/png2pdf.py
WeReadScan-0.8.7.dist-info/METADATA
WeReadScan-0.8.7.dist-info/WHEEL
WeReadScan-0.8.7.dist-info/top_level.txt
WeReadScan-0.8.7.dist-info/RECORD
