Metadata-Version: 2.1
Name: WeReadScan
Version: 0.8.7
Summary: WeRead PDF Scanner
Home-page: https://github.com/Algebra-FUN/WeReadScan
Author: Algebra-FUN
Author-email: 2593991307@qq.com
License: GPL Licence
Keywords: weread,scan,pdf,convert,selenium
Platform: window
Requires-Python: >=3.6
Requires-Dist: pillow
Requires-Dist: numpy
Requires-Dist: matplotlib
Requires-Dist: img2pdf
Requires-Dist: opencv-python
Requires-Dist: selenium
